[{"contributors":null,"truncated":false,"text":"@KhaledBeydoun &lt;----Disgrace. Only concerned about Liberal Talking points and NOT the Hostages being terrorized. Sickening. #sydneysiege","in_reply_to_status_id":544391323214573568,"id":544393785476935680,"favorite_count":0,"source":"<a href=\"http://twitter.com\" rel=\"nofollow\">Twitter Web Client</a>","retweeted":false,"coordinates":null,"entities":{"symbols":[],"user_mentions":[{"id":2163076560,"indices":[0,14],"id_str":"2163076560","screen_name":"KhaledBeydoun","name":"Khaled Bey"}],"hashtags":[{"indices":[127,139],"text":"sydneysiege"}],"urls":[]},"in_reply_to_screen_name":"KhaledBeydoun","id_str":"544393785476935680","retweet_count":1,"in_reply_to_user_id":2163076560,"favorited":false,"user":{"follow_request_sent":false,"profile_use_background_image":true,"profile_text_color":"333333","default_profile_image":false,"id":2251196504,"profile_background_image_url_https":"https://abs.twimg.com/images/themes/theme1/bg.png","verified":false,"profile_location":null,"profile_image_url_https":"https://pbs.twimg.com/profile_images/413114096146329600/GtPLcpFw_normal.jpeg","profile_sidebar_fill_color":"DDEEF6","entities":{"description":{"urls":[]}},"followers_count":1093,"profile_sidebar_border_color":"C0DEED","id_str":"2251196504","profile_background_color":"C0DEED","listed_count":31,"is_translation_enabled":false,"utc_offset":null,"statuses_count":7717,"description":"Patriot. Freedom Lover. Reagan Conservative. I want my country back!","friends_count":1270,"location":"Dallas TX","profile_link_color":"0084B4","profile_image_url":"http://pbs.twimg.com/profile_images/413114096146329600/GtPLcpFw_normal.jpeg","following":false,"geo_enabled":false,"profile_banner_url":"https://pbs.twimg.com/profile_banners/2251196504/1387332021","profile_background_image_url":"http://abs.twimg.com/images/themes/theme1/bg.png","name":"Bob Johnson","lang":"en","profile_background_tile":false,"favourites_count":875,"screen_name":"RobertDaPatriot","notifications":false,"url":null,"created_at":"Wed Dec 18 01:03:08 +0000 2013","contributors_enabled":false,"time_zone":null,"protected":false,"default_profile":true,"is_translator":false},"geo":null,"in_reply_to_user_id_str":"2163076560","lang":"en","created_at":"Mon Dec 15 07:29:27 +0000 2014","in_reply_to_status_id_str":"544391323214573568","place":null},
{"contributors":null,"truncated":false,"text":"@RobertDaPatriot @KhaledBeydoun Australians are Muslim and every other religion, Bob.I understand why this must be said today.","in_reply_to_status_id":544393785476935680,"id":544406052872003584,"favorite_count":0,"source":"<a href=\"http://twitter.com\" rel=\"nofollow\">Twitter Web Client</a>","retweeted":false,"coordinates":null,"entities":{"symbols":[],"user_mentions":[{"id":2251196504,"indices":[0,16],"id_str":"2251196504","screen_name":"RobertDaPatriot","name":"Bob Johnson"},{"id":2163076560,"indices":[17,31],"id_str":"2163076560","screen_name":"KhaledBeydoun","name":"Khaled Bey"}],"hashtags":[],"urls":[]},"in_reply_to_screen_name":"RobertDaPatriot","id_str":"544406052872003584","retweet_count":0,"in_reply_to_user_id":2251196504,"favorited":false,"user":{"follow_request_sent":false,"profile_use_background_image":true,"profile_text_color":"663B12","default_profile_image":false,"id":363509031,"profile_background_image_url_https":"https://abs.twimg.com/images/themes/theme2/bg.gif","verified":false,"profile_location":null,"profile_image_url_https":"https://pbs.twimg.com/profile_images/455621417468317696/cG5AzIIy_normal.jpeg","profile_sidebar_fill_color":"DAECF4","entities":{"description":{"urls":[]}},"followers_count":590,"profile_sidebar_border_color":"C6E2EE","id_str":"363509031","profile_background_color":"C6E2EE","listed_count":11,"is_translation_enabled":false,"utc_offset":39600,"statuses_count":9379,"description":"","friends_count":854,"location":"","profile_link_color":"1F98C7","profile_image_url":"http://pbs.twimg.com/profile_images/455621417468317696/cG5AzIIy_normal.jpeg","following":false,"geo_enabled":false,"profile_background_image_url":"http://abs.twimg.com/images/themes/theme2/bg.gif","name":"jansci","lang":"en","profile_background_tile":false,"favourites_count":48832,"screen_name":"thereminfan","notifications":false,"url":null,"created_at":"Sun Aug 28 06:00:59 +0000 2011","contributors_enabled":false,"time_zone":"Sydney","protected":false,"default_profile":false,"is_translator":false},"geo":null,"in_reply_to_user_id_str":"2251196504","lang":"en","created_at":"Mon Dec 15 08:18:12 +0000 2014","in_reply_to_status_id_str":"544393785476935680","place":null},
{"contributors":null,"truncated":false,"text":"@KhaledBeydoun @dramarams beautiful picture. :)","in_reply_to_status_id":544391323214573568,"id":544417213860438016,"favorite_count":1,"source":"<a href=\"http://twitterrific.com\" rel=\"nofollow\">Twitterrific</a>","retweeted":false,"coordinates":null,"entities":{"symbols":[],"user_mentions":[{"id":2163076560,"indices":[0,14],"id_str":"2163076560","screen_name":"KhaledBeydoun","name":"Khaled Bey"},{"id":236077169,"indices":[15,25],"id_str":"236077169","screen_name":"dramarams","name":"Ramy Eletreby"}],"hashtags":[],"urls":[]},"in_reply_to_screen_name":"KhaledBeydoun","id_str":"544417213860438016","retweet_count":0,"in_reply_to_user_id":2163076560,"favorited":false,"user":{"follow_request_sent":false,"profile_use_background_image":true,"profile_text_color":"333333","default_profile_image":false,"id":63963528,"profile_background_image_url_https":"https://pbs.twimg.com/profile_background_images/201244177/thing.7198598.l.jpg","verified":false,"profile_location":null,"profile_image_url_https":"https://pbs.twimg.com/profile_images/543380320960004097/gGnIab9l_normal.png","profile_sidebar_fill_color":"DDEEF6","entities":{"url":{"urls":[{"url":"http://t.co/pidNxk2Fu6","indices":[0,22],"expanded_url":"http://www.screenthemes.org","display_url":"screenthemes.org"}]},"description":{"urls":[]}},"followers_count":242,"profile_sidebar_border_color":"C0DEED","id_str":"63963528","profile_background_color":"C0DEED","listed_count":5,"is_translation_enabled":false,"utc_offset":39600,"statuses_count":771,"description":"Weekly film, tv, screen & digital media music, news & interview programme on 3MBSfm  produced/presented by film critic Carol van Opstal #screenthemes","friends_count":254,"location":"Australia","profile_link_color":"0084B4","profile_image_url":"http://pbs.twimg.com/profile_images/543380320960004097/gGnIab9l_normal.png","following":false,"geo_enabled":false,"profile_background_image_url":"http://pbs.twimg.com/profile_background_images/201244177/thing.7198598.l.jpg","name":"Screenthemes","lang":"en","profile_background_tile":true,"favourites_count":6,"screen_name":"screenthemes","notifications":false,"url":"http://t.co/pidNxk2Fu6","created_at":"Sat Aug 08 13:14:40 +0000 2009","contributors_enabled":false,"time_zone":"Melbourne","protected":false,"default_profile":false,"is_translator":false},"geo":null,"in_reply_to_user_id_str":"2163076560","lang":"en","created_at":"Mon Dec 15 09:02:33 +0000 2014","in_reply_to_status_id_str":"544391323214573568","place":null},
{"contributors":null,"truncated":false,"text":"@KhaledBeydoun no need to twist things , this is you're religion honey","in_reply_to_status_id":544391323214573568,"id":544427433793830912,"favorite_count":0,"source":"<a href=\"http://twitter.com\" rel=\"nofollow\">Twitter Web Client</a>","retweeted":false,"coordinates":null,"entities":{"symbols":[],"user_mentions":[{"id":2163076560,"indices":[0,14],"id_str":"2163076560","screen_name":"KhaledBeydoun","name":"Khaled Bey"}],"hashtags":[],"urls":[]},"in_reply_to_screen_name":"KhaledBeydoun","id_str":"544427433793830912","retweet_count":0,"in_reply_to_user_id":2163076560,"favorited":false,"user":{"follow_request_sent":false,"profile_use_background_image":true,"profile_text_color":"333333","default_profile_image":false,"id":789398972,"profile_background_image_url_https":"https://abs.twimg.com/images/themes/theme1/bg.png","verified":false,"profile_location":null,"profile_image_url_https":"https://pbs.twimg.com/profile_images/495542185647812608/2XUe6zjG_normal.jpeg","profile_sidebar_fill_color":"DDEEF6","entities":{"description":{"urls":[]}},"followers_count":85,"profile_sidebar_border_color":"C0DEED","id_str":"789398972","profile_background_color":"C0DEED","listed_count":2,"is_translation_enabled":false,"utc_offset":-25200,"statuses_count":1491,"description":"","friends_count":118,"location":"","profile_link_color":"0084B4","profile_image_url":"http://pbs.twimg.com/profile_images/495542185647812608/2XUe6zjG_normal.jpeg","following":false,"geo_enabled":false,"profile_banner_url":"https://pbs.twimg.com/profile_banners/789398972/1406981453","profile_background_image_url":"http://abs.twimg.com/images/themes/theme1/bg.png","name":"SelenaWayToGo...Mez ","lang":"en","profile_background_tile":false,"favourites_count":167,"screen_name":"Selenator4eveaa","notifications":false,"url":null,"created_at":"Wed Aug 29 13:57:23 +0000 2012","contributors_enabled":false,"time_zone":"Arizona","protected":false,"default_profile":true,"is_translator":false},"geo":null,"in_reply_to_user_id_str":"2163076560","lang":"en","created_at":"Mon Dec 15 09:43:09 +0000 2014","in_reply_to_status_id_str":"544391323214573568","place":null},
{"contributors":null,"truncated":false,"text":"@Selenator4eveaa *your honey, learn to spell before talking shit","in_reply_to_status_id":544427433793830912,"id":544470680855928832,"favorite_count":0,"source":"<a href=\"http://twitter.com/download/iphone\" rel=\"nofollow\">Twitter for iPhone</a>","retweeted":false,"coordinates":null,"entities":{"symbols":[],"user_mentions":[{"id":789398972,"indices":[0,16],"id_str":"789398972","screen_name":"Selenator4eveaa","name":"SelenaWayToGo...Mez "}],"hashtags":[],"urls":[]},"in_reply_to_screen_name":"Selenator4eveaa","id_str":"544470680855928832","retweet_count":0,"in_reply_to_user_id":789398972,"favorited":false,"user":{"follow_request_sent":false,"profile_use_background_image":true,"profile_text_color":"333333","default_profile_image":false,"id":2171636099,"profile_background_image_url_https":"https://abs.twimg.com/images/themes/theme1/bg.png","verified":false,"profile_location":null,"profile_image_url_https":"https://pbs.twimg.com/profile_images/588780249359454208/sQ18UbYs_normal.jpg","profile_sidebar_fill_color":"DDEEF6","entities":{"description":{"urls":[]}},"followers_count":2202,"profile_sidebar_border_color":"C0DEED","id_str":"2171636099","profile_background_color":"C0DEED","listed_count":11,"is_translation_enabled":false,"utc_offset":null,"statuses_count":38973,"description":"“There’s a devil in your smile that’s chasing me, and every time I turn around it’s only gaining speed”","friends_count":2086,"location":"","profile_link_color":"0084B4","profile_image_url":"http://pbs.twimg.com/profile_images/588780249359454208/sQ18UbYs_normal.jpg","following":false,"geo_enabled":false,"profile_banner_url":"https://pbs.twimg.com/profile_banners/2171636099/1418526331","profile_background_image_url":"http://abs.twimg.com/images/themes/theme1/bg.png","name":"anus","lang":"en","profile_background_tile":false,"favourites_count":19518,"screen_name":"bathsaltsniall","notifications":false,"url":null,"created_at":"Thu Nov 07 03:33:35 +0000 2013","contributors_enabled":false,"time_zone":null,"protected":false,"default_profile":true,"is_translator":false},"geo":null,"in_reply_to_user_id_str":"789398972","lang":"en","created_at":"Mon Dec 15 12:35:00 +0000 2014","in_reply_to_status_id_str":"544427433793830912","place":null},
{"contributors":null,"truncated":false,"text":"@KhaledBeydoun @selenaftprada why what happened in sydney","in_reply_to_status_id":544391323214573568,"id":544508589734256640,"favorite_count":0,"source":"<a href=\"http://twitter.com/download/android\" rel=\"nofollow\">Twitter for Android</a>","retweeted":false,"coordinates":null,"entities":{"symbols":[],"user_mentions":[{"id":2163076560,"indices":[0,14],"id_str":"2163076560","screen_name":"KhaledBeydoun","name":"Khaled Bey"},{"id":2361194822,"indices":[15,29],"id_str":"2361194822","screen_name":"selenaftprada","name":"Selena Gomez"}],"hashtags":[],"urls":[]},"in_reply_to_screen_name":"KhaledBeydoun","id_str":"544508589734256640","retweet_count":0,"in_reply_to_user_id":2163076560,"favorited":false,"user":{"follow_request_sent":false,"profile_use_background_image":true,"profile_text_color":"333333","default_profile_image":false,"id":2792309533,"profile_background_image_url_https":"https://abs.twimg.com/images/themes/theme1/bg.png","verified":false,"profile_location":null,"profile_image_url_https":"https://pbs.twimg.com/profile_images/507965571577569280/GjSmBb5p_normal.jpeg","profile_sidebar_fill_color":"DDEEF6","entities":{"description":{"urls":[]}},"followers_count":15,"profile_sidebar_border_color":"C0DEED","id_str":"2792309533","profile_background_color":"C0DEED","listed_count":0,"is_translation_enabled":false,"utc_offset":null,"statuses_count":56,"description":"","friends_count":212,"location":"","profile_link_color":"0084B4","profile_image_url":"http://pbs.twimg.com/profile_images/507965571577569280/GjSmBb5p_normal.jpeg","following":false,"geo_enabled":false,"profile_background_image_url":"http://abs.twimg.com/images/themes/theme1/bg.png","name":"saeed badshah","lang":"en","profile_background_tile":false,"favourites_count":15,"screen_name":"saeedbadshah50","notifications":false,"url":null,"created_at":"Fri Sep 05 16:33:11 +0000 2014","contributors_enabled":false,"time_zone":null,"protected":false,"default_profile":true,"is_translator":false},"geo":null,"in_reply_to_user_id_str":"2163076560","lang":"en","created_at":"Mon Dec 15 15:05:38 +0000 2014","in_reply_to_status_id_str":"544391323214573568","place":null},
{"contributors":null,"truncated":false,"text":"@screenthemes @KhaledBeydoun @dramarams what drama","in_reply_to_status_id":544417213860438016,"id":544508785306263552,"favorite_count":0,"source":"<a href=\"http://twitter.com/download/android\" rel=\"nofollow\">Twitter for Android</a>","retweeted":false,"coordinates":null,"entities":{"symbols":[],"user_mentions":[{"id":63963528,"indices":[0,13],"id_str":"63963528","screen_name":"screenthemes","name":"Screenthemes"},{"id":2163076560,"indices":[14,28],"id_str":"2163076560","screen_name":"KhaledBeydoun","name":"Khaled Bey"},{"id":236077169,"indices":[29,39],"id_str":"236077169","screen_name":"dramarams","name":"Ramy Eletreby"}],"hashtags":[],"urls":[]},"in_reply_to_screen_name":"screenthemes","id_str":"544508785306263552","retweet_count":0,"in_reply_to_user_id":63963528,"favorited":false,"user":{"follow_request_sent":false,"profile_use_background_image":true,"profile_text_color":"333333","default_profile_image":false,"id":2792309533,"profile_background_image_url_https":"https://abs.twimg.com/images/themes/theme1/bg.png","verified":false,"profile_location":null,"profile_image_url_https":"https://pbs.twimg.com/profile_images/507965571577569280/GjSmBb5p_normal.jpeg","profile_sidebar_fill_color":"DDEEF6","entities":{"description":{"urls":[]}},"followers_count":15,"profile_sidebar_border_color":"C0DEED","id_str":"2792309533","profile_background_color":"C0DEED","listed_count":0,"is_translation_enabled":false,"utc_offset":null,"statuses_count":56,"description":"","friends_count":212,"location":"","profile_link_color":"0084B4","profile_image_url":"http://pbs.twimg.com/profile_images/507965571577569280/GjSmBb5p_normal.jpeg","following":false,"geo_enabled":false,"profile_background_image_url":"http://abs.twimg.com/images/themes/theme1/bg.png","name":"saeed badshah","lang":"en","profile_background_tile":false,"favourites_count":15,"screen_name":"saeedbadshah50","notifications":false,"url":null,"created_at":"Fri Sep 05 16:33:11 +0000 2014","contributors_enabled":false,"time_zone":null,"protected":false,"default_profile":true,"is_translator":false},"geo":null,"in_reply_to_user_id_str":"63963528","lang":"en","created_at":"Mon Dec 15 15:06:25 +0000 2014","in_reply_to_status_id_str":"544417213860438016","place":null},
{"contributors":null,"truncated":false,"text":"@saeedbadshah50 @KhaledBeydoun hostages were taken in a café in Sydney.","in_reply_to_status_id":544508589734256640,"id":544543050383765504,"favorite_count":0,"source":"<a href=\"http://twitter.com\" rel=\"nofollow\">Twitter Web Client</a>","retweeted":false,"coordinates":null,"entities":{"symbols":[],"user_mentions":[{"id":2792309533,"indices":[0,15],"id_str":"2792309533","screen_name":"saeedbadshah50","name":"saeed badshah"},{"id":2163076560,"indices":[16,30],"id_str":"2163076560","screen_name":"KhaledBeydoun","name":"Khaled Bey"}],"hashtags":[],"urls":[]},"in_reply_to_screen_name":"saeedbadshah50","id_str":"544543050383765504","retweet_count":0,"in_reply_to_user_id":2792309533,"favorited":false,"user":{"follow_request_sent":false,"profile_use_background_image":true,"profile_text_color":"3C3940","default_profile_image":false,"id":2361194822,"profile_background_image_url_https":"https://pbs.twimg.com/profile_background_images/480467914462461952/9CkWm3oY.jpeg","verified":false,"profile_location":null,"profile_image_url_https":"https://pbs.twimg.com/profile_images/589150197432901632/M_T8-y56_normal.png","profile_sidebar_fill_color":"95E8EC","entities":{"url":{"urls":[{"url":"http://t.co/xCtMQBjXGd","indices":[0,22],"expanded_url":"http://ask.fm/selenagismyidol","display_url":"ask.fm/selenagismyidol"}]},"description":{"urls":[]}},"followers_count":5320,"profile_sidebar_border_color":"FFFFFF","id_str":"2361194822","profile_background_color":"0099B9","listed_count":17,"is_translation_enabled":false,"utc_offset":7200,"statuses_count":17008,"description":"Here for Selena, not for your opinion. Love yourself first.","friends_count":4296,"location":"✈️","profile_link_color":"FFCC4D","profile_image_url":"http://pbs.twimg.com/profile_images/589150197432901632/M_T8-y56_normal.png","following":false,"geo_enabled":true,"profile_banner_url":"https://pbs.twimg.com/profile_banners/2361194822/1418240906","profile_background_image_url":"http://pbs.twimg.com/profile_background_images/480467914462461952/9CkWm3oY.jpeg","name":"Selena Gomez","lang":"es","profile_background_tile":true,"favourites_count":2030,"screen_name":"selenaftprada","notifications":false,"url":"http://t.co/xCtMQBjXGd","created_at":"Tue Feb 25 14:45:16 +0000 2014","contributors_enabled":false,"time_zone":"Athens","protected":false,"default_profile":false,"is_translator":false},"geo":null,"in_reply_to_user_id_str":"2792309533","lang":"en","created_at":"Mon Dec 15 17:22:34 +0000 2014","in_reply_to_status_id_str":"544508589734256640","place":{"full_name":"Grand Prairie, TX","url":"https://api.twitter.com/1.1/geo/id/a9b50065bfbb3fa9.json","country":"United States","place_type":"city","bounding_box":{"type":"Polygon","coordinates":[[[-97.065649,32.720529],[-96.924017,32.720529],[-96.924017,32.816653],[-97.065649,32.816653]]]},"contained_within":[],"country_code":"US","attributes":{},"id":"a9b50065bfbb3fa9","name":"Grand Prairie"}},
{"contributors":null,"truncated":false,"text":"@selenaftprada @KhaledBeydoun salena I love u add me on Facebook my id saeedbadshah50@yahoo.com","in_reply_to_status_id":544543050383765504,"id":544568476942098432,"favorite_count":0,"source":"<a href=\"http://twitter.com/download/android\" rel=\"nofollow\">Twitter for Android</a>","retweeted":false,"coordinates":null,"entities":{"symbols":[],"user_mentions":[{"id":2361194822,"indices":[0,14],"id_str":"2361194822","screen_name":"selenaftprada","name":"Selena Gomez"},{"id":2163076560,"indices":[15,29],"id_str":"2163076560","screen_name":"KhaledBeydoun","name":"Khaled Bey"}],"hashtags":[],"urls":[]},"in_reply_to_screen_name":"selenaftprada","id_str":"544568476942098432","retweet_count":0,"in_reply_to_user_id":2361194822,"favorited":false,"user":{"follow_request_sent":false,"profile_use_background_image":true,"profile_text_color":"333333","default_profile_image":false,"id":2792309533,"profile_background_image_url_https":"https://abs.twimg.com/images/themes/theme1/bg.png","verified":false,"profile_location":null,"profile_image_url_https":"https://pbs.twimg.com/profile_images/507965571577569280/GjSmBb5p_normal.jpeg","profile_sidebar_fill_color":"DDEEF6","entities":{"description":{"urls":[]}},"followers_count":15,"profile_sidebar_border_color":"C0DEED","id_str":"2792309533","profile_background_color":"C0DEED","listed_count":0,"is_translation_enabled":false,"utc_offset":null,"statuses_count":56,"description":"","friends_count":212,"location":"","profile_link_color":"0084B4","profile_image_url":"http://pbs.twimg.com/profile_images/507965571577569280/GjSmBb5p_normal.jpeg","following":false,"geo_enabled":false,"profile_background_image_url":"http://abs.twimg.com/images/themes/theme1/bg.png","name":"saeed badshah","lang":"en","profile_background_tile":false,"favourites_count":15,"screen_name":"saeedbadshah50","notifications":false,"url":null,"created_at":"Fri Sep 05 16:33:11 +0000 2014","contributors_enabled":false,"time_zone":null,"protected":false,"default_profile":true,"is_translator":false},"geo":null,"in_reply_to_user_id_str":"2361194822","lang":"en","created_at":"Mon Dec 15 19:03:37 +0000 2014","in_reply_to_status_id_str":"544543050383765504","place":null},
{"contributors":null,"truncated":false,"text":"@saeedbadshah50 @KhaledBeydoun i am not selena.","in_reply_to_status_id":544568476942098432,"id":544569746310840320,"favorite_count":0,"source":"<a href=\"http://twitter.com\" rel=\"nofollow\">Twitter Web Client</a>","retweeted":false,"coordinates":null,"entities":{"symbols":[],"user_mentions":[{"id":2792309533,"indices":[0,15],"id_str":"2792309533","screen_name":"saeedbadshah50","name":"saeed badshah"},{"id":2163076560,"indices":[16,30],"id_str":"2163076560","screen_name":"KhaledBeydoun","name":"Khaled Bey"}],"hashtags":[],"urls":[]},"in_reply_to_screen_name":"saeedbadshah50","id_str":"544569746310840320","retweet_count":0,"in_reply_to_user_id":2792309533,"favorited":false,"user":{"follow_request_sent":false,"profile_use_background_image":true,"profile_text_color":"3C3940","default_profile_image":false,"id":2361194822,"profile_background_image_url_https":"https://pbs.twimg.com/profile_background_images/480467914462461952/9CkWm3oY.jpeg","verified":false,"profile_location":null,"profile_image_url_https":"https://pbs.twimg.com/profile_images/589150197432901632/M_T8-y56_normal.png","profile_sidebar_fill_color":"95E8EC","entities":{"url":{"urls":[{"url":"http://t.co/xCtMQBjXGd","indices":[0,22],"expanded_url":"http://ask.fm/selenagismyidol","display_url":"ask.fm/selenagismyidol"}]},"description":{"urls":[]}},"followers_count":5320,"profile_sidebar_border_color":"FFFFFF","id_str":"2361194822","profile_background_color":"0099B9","listed_count":17,"is_translation_enabled":false,"utc_offset":7200,"statuses_count":17008,"description":"Here for Selena, not for your opinion. Love yourself first.","friends_count":4296,"location":"✈️","profile_link_color":"FFCC4D","profile_image_url":"http://pbs.twimg.com/profile_images/589150197432901632/M_T8-y56_normal.png","following":false,"geo_enabled":true,"profile_banner_url":"https://pbs.twimg.com/profile_banners/2361194822/1418240906","profile_background_image_url":"http://pbs.twimg.com/profile_background_images/480467914462461952/9CkWm3oY.jpeg","name":"Selena Gomez","lang":"es","profile_background_tile":true,"favourites_count":2030,"screen_name":"selenaftprada","notifications":false,"url":"http://t.co/xCtMQBjXGd","created_at":"Tue Feb 25 14:45:16 +0000 2014","contributors_enabled":false,"time_zone":"Athens","protected":false,"default_profile":false,"is_translator":false},"geo":null,"in_reply_to_user_id_str":"2792309533","lang":"en","created_at":"Mon Dec 15 19:08:39 +0000 2014","in_reply_to_status_id_str":"544568476942098432","place":{"full_name":"Grand Prairie, TX","url":"https://api.twitter.com/1.1/geo/id/a9b50065bfbb3fa9.json","country":"United States","place_type":"city","bounding_box":{"type":"Polygon","coordinates":[[[-97.065649,32.720529],[-96.924017,32.720529],[-96.924017,32.816653],[-97.065649,32.816653]]]},"contained_within":[],"country_code":"US","attributes":{},"id":"a9b50065bfbb3fa9","name":"Grand Prairie"}},
{"contributors":null,"truncated":false,"text":"@selenaftprada @KhaledBeydoun who are u","in_reply_to_status_id":544569746310840320,"id":544569882264612864,"favorite_count":0,"source":"<a href=\"http://twitter.com/download/android\" rel=\"nofollow\">Twitter for Android</a>","retweeted":false,"coordinates":null,"entities":{"symbols":[],"user_mentions":[{"id":2361194822,"indices":[0,14],"id_str":"2361194822","screen_name":"selenaftprada","name":"Selena Gomez"},{"id":2163076560,"indices":[15,29],"id_str":"2163076560","screen_name":"KhaledBeydoun","name":"Khaled Bey"}],"hashtags":[],"urls":[]},"in_reply_to_screen_name":"selenaftprada","id_str":"544569882264612864","retweet_count":0,"in_reply_to_user_id":2361194822,"favorited":false,"user":{"follow_request_sent":false,"profile_use_background_image":true,"profile_text_color":"333333","default_profile_image":false,"id":2792309533,"profile_background_image_url_https":"https://abs.twimg.com/images/themes/theme1/bg.png","verified":false,"profile_location":null,"profile_image_url_https":"https://pbs.twimg.com/profile_images/507965571577569280/GjSmBb5p_normal.jpeg","profile_sidebar_fill_color":"DDEEF6","entities":{"description":{"urls":[]}},"followers_count":15,"profile_sidebar_border_color":"C0DEED","id_str":"2792309533","profile_background_color":"C0DEED","listed_count":0,"is_translation_enabled":false,"utc_offset":null,"statuses_count":56,"description":"","friends_count":212,"location":"","profile_link_color":"0084B4","profile_image_url":"http://pbs.twimg.com/profile_images/507965571577569280/GjSmBb5p_normal.jpeg","following":false,"geo_enabled":false,"profile_background_image_url":"http://abs.twimg.com/images/themes/theme1/bg.png","name":"saeed badshah","lang":"en","profile_background_tile":false,"favourites_count":15,"screen_name":"saeedbadshah50","notifications":false,"url":null,"created_at":"Fri Sep 05 16:33:11 +0000 2014","contributors_enabled":false,"time_zone":null,"protected":false,"default_profile":true,"is_translator":false},"geo":null,"in_reply_to_user_id_str":"2361194822","lang":"en","created_at":"Mon Dec 15 19:09:12 +0000 2014","in_reply_to_status_id_str":"544569746310840320","place":null},
{"contributors":null,"truncated":false,"text":"@saeedbadshah50 @KhaledBeydoun selenator","in_reply_to_status_id":544569882264612864,"id":544569966029447170,"favorite_count":0,"source":"<a href=\"http://twitter.com\" rel=\"nofollow\">Twitter Web Client</a>","retweeted":false,"coordinates":null,"entities":{"symbols":[],"user_mentions":[{"id":2792309533,"indices":[0,15],"id_str":"2792309533","screen_name":"saeedbadshah50","name":"saeed badshah"},{"id":2163076560,"indices":[16,30],"id_str":"2163076560","screen_name":"KhaledBeydoun","name":"Khaled Bey"}],"hashtags":[],"urls":[]},"in_reply_to_screen_name":"saeedbadshah50","id_str":"544569966029447170","retweet_count":0,"in_reply_to_user_id":2792309533,"favorited":false,"user":{"follow_request_sent":false,"profile_use_background_image":true,"profile_text_color":"3C3940","default_profile_image":false,"id":2361194822,"profile_background_image_url_https":"https://pbs.twimg.com/profile_background_images/480467914462461952/9CkWm3oY.jpeg","verified":false,"profile_location":null,"profile_image_url_https":"https://pbs.twimg.com/profile_images/589150197432901632/M_T8-y56_normal.png","profile_sidebar_fill_color":"95E8EC","entities":{"url":{"urls":[{"url":"http://t.co/xCtMQBjXGd","indices":[0,22],"expanded_url":"http://ask.fm/selenagismyidol","display_url":"ask.fm/selenagismyidol"}]},"description":{"urls":[]}},"followers_count":5320,"profile_sidebar_border_color":"FFFFFF","id_str":"2361194822","profile_background_color":"0099B9","listed_count":17,"is_translation_enabled":false,"utc_offset":7200,"statuses_count":17008,"description":"Here for Selena, not for your opinion. Love yourself first.","friends_count":4296,"location":"✈️","profile_link_color":"FFCC4D","profile_image_url":"http://pbs.twimg.com/profile_images/589150197432901632/M_T8-y56_normal.png","following":false,"geo_enabled":true,"profile_banner_url":"https://pbs.twimg.com/profile_banners/2361194822/1418240906","profile_background_image_url":"http://pbs.twimg.com/profile_background_images/480467914462461952/9CkWm3oY.jpeg","name":"Selena Gomez","lang":"es","profile_background_tile":true,"favourites_count":2030,"screen_name":"selenaftprada","notifications":false,"url":"http://t.co/xCtMQBjXGd","created_at":"Tue Feb 25 14:45:16 +0000 2014","contributors_enabled":false,"time_zone":"Athens","protected":false,"default_profile":false,"is_translator":false},"geo":null,"in_reply_to_user_id_str":"2792309533","lang":"ro","created_at":"Mon Dec 15 19:09:32 +0000 2014","in_reply_to_status_id_str":"544569882264612864","place":{"full_name":"Grand Prairie, TX","url":"https://api.twitter.com/1.1/geo/id/a9b50065bfbb3fa9.json","country":"United States","place_type":"city","bounding_box":{"type":"Polygon","coordinates":[[[-97.065649,32.720529],[-96.924017,32.720529],[-96.924017,32.816653],[-97.065649,32.816653]]]},"contained_within":[],"country_code":"US","attributes":{},"id":"a9b50065bfbb3fa9","name":"Grand Prairie"}},
{"contributors":null,"truncated":false,"text":"@selenaftprada @KhaledBeydoun u r khalid","in_reply_to_status_id":544569746310840320,"id":544570006244048896,"favorite_count":0,"source":"<a href=\"http://twitter.com/download/android\" rel=\"nofollow\">Twitter for Android</a>","retweeted":false,"coordinates":null,"entities":{"symbols":[],"user_mentions":[{"id":2361194822,"indices":[0,14],"id_str":"2361194822","screen_name":"selenaftprada","name":"Selena Gomez"},{"id":2163076560,"indices":[15,29],"id_str":"2163076560","screen_name":"KhaledBeydoun","name":"Khaled Bey"}],"hashtags":[],"urls":[]},"in_reply_to_screen_name":"selenaftprada","id_str":"544570006244048896","retweet_count":0,"in_reply_to_user_id":2361194822,"favorited":false,"user":{"follow_request_sent":false,"profile_use_background_image":true,"profile_text_color":"333333","default_profile_image":false,"id":2792309533,"profile_background_image_url_https":"https://abs.twimg.com/images/themes/theme1/bg.png","verified":false,"profile_location":null,"profile_image_url_https":"https://pbs.twimg.com/profile_images/507965571577569280/GjSmBb5p_normal.jpeg","profile_sidebar_fill_color":"DDEEF6","entities":{"description":{"urls":[]}},"followers_count":15,"profile_sidebar_border_color":"C0DEED","id_str":"2792309533","profile_background_color":"C0DEED","listed_count":0,"is_translation_enabled":false,"utc_offset":null,"statuses_count":56,"description":"","friends_count":212,"location":"","profile_link_color":"0084B4","profile_image_url":"http://pbs.twimg.com/profile_images/507965571577569280/GjSmBb5p_normal.jpeg","following":false,"geo_enabled":false,"profile_background_image_url":"http://abs.twimg.com/images/themes/theme1/bg.png","name":"saeed badshah","lang":"en","profile_background_tile":false,"favourites_count":15,"screen_name":"saeedbadshah50","notifications":false,"url":null,"created_at":"Fri Sep 05 16:33:11 +0000 2014","contributors_enabled":false,"time_zone":null,"protected":false,"default_profile":true,"is_translator":false},"geo":null,"in_reply_to_user_id_str":"2361194822","lang":"en","created_at":"Mon Dec 15 19:09:41 +0000 2014","in_reply_to_status_id_str":"544569746310840320","place":null},
{"contributors":null,"truncated":false,"text":"@selenaftprada @KhaledBeydoun where u from","in_reply_to_status_id":544569966029447170,"id":544570171218612224,"favorite_count":0,"source":"<a href=\"http://twitter.com/download/android\" rel=\"nofollow\">Twitter for Android</a>","retweeted":false,"coordinates":null,"entities":{"symbols":[],"user_mentions":[{"id":2361194822,"indices":[0,14],"id_str":"2361194822","screen_name":"selenaftprada","name":"Selena Gomez"},{"id":2163076560,"indices":[15,29],"id_str":"2163076560","screen_name":"KhaledBeydoun","name":"Khaled Bey"}],"hashtags":[],"urls":[]},"in_reply_to_screen_name":"selenaftprada","id_str":"544570171218612224","retweet_count":0,"in_reply_to_user_id":2361194822,"favorited":false,"user":{"follow_request_sent":false,"profile_use_background_image":true,"profile_text_color":"333333","default_profile_image":false,"id":2792309533,"profile_background_image_url_https":"https://abs.twimg.com/images/themes/theme1/bg.png","verified":false,"profile_location":null,"profile_image_url_https":"https://pbs.twimg.com/profile_images/507965571577569280/GjSmBb5p_normal.jpeg","profile_sidebar_fill_color":"DDEEF6","entities":{"description":{"urls":[]}},"followers_count":15,"profile_sidebar_border_color":"C0DEED","id_str":"2792309533","profile_background_color":"C0DEED","listed_count":0,"is_translation_enabled":false,"utc_offset":null,"statuses_count":56,"description":"","friends_count":212,"location":"","profile_link_color":"0084B4","profile_image_url":"http://pbs.twimg.com/profile_images/507965571577569280/GjSmBb5p_normal.jpeg","following":false,"geo_enabled":false,"profile_background_image_url":"http://abs.twimg.com/images/themes/theme1/bg.png","name":"saeed badshah","lang":"en","profile_background_tile":false,"favourites_count":15,"screen_name":"saeedbadshah50","notifications":false,"url":null,"created_at":"Fri Sep 05 16:33:11 +0000 2014","contributors_enabled":false,"time_zone":null,"protected":false,"default_profile":true,"is_translator":false},"geo":null,"in_reply_to_user_id_str":"2361194822","lang":"en","created_at":"Mon Dec 15 19:10:21 +0000 2014","in_reply_to_status_id_str":"544569966029447170","place":null},
{"contributors":null,"truncated":false,"text":"@saeedbadshah50 @KhaledBeydoun no","in_reply_to_status_id":544570006244048896,"id":544570202101645312,"favorite_count":0,"source":"<a href=\"http://twitter.com\" rel=\"nofollow\">Twitter Web Client</a>","retweeted":false,"coordinates":null,"entities":{"symbols":[],"user_mentions":[{"id":2792309533,"indices":[0,15],"id_str":"2792309533","screen_name":"saeedbadshah50","name":"saeed badshah"},{"id":2163076560,"indices":[16,30],"id_str":"2163076560","screen_name":"KhaledBeydoun","name":"Khaled Bey"}],"hashtags":[],"urls":[]},"in_reply_to_screen_name":"saeedbadshah50","id_str":"544570202101645312","retweet_count":0,"in_reply_to_user_id":2792309533,"favorited":false,"user":{"follow_request_sent":false,"profile_use_background_image":true,"profile_text_color":"3C3940","default_profile_image":false,"id":2361194822,"profile_background_image_url_https":"https://pbs.twimg.com/profile_background_images/480467914462461952/9CkWm3oY.jpeg","verified":false,"profile_location":null,"profile_image_url_https":"https://pbs.twimg.com/profile_images/589150197432901632/M_T8-y56_normal.png","profile_sidebar_fill_color":"95E8EC","entities":{"url":{"urls":[{"url":"http://t.co/xCtMQBjXGd","indices":[0,22],"expanded_url":"http://ask.fm/selenagismyidol","display_url":"ask.fm/selenagismyidol"}]},"description":{"urls":[]}},"followers_count":5320,"profile_sidebar_border_color":"FFFFFF","id_str":"2361194822","profile_background_color":"0099B9","listed_count":17,"is_translation_enabled":false,"utc_offset":7200,"statuses_count":17008,"description":"Here for Selena, not for your opinion. Love yourself first.","friends_count":4296,"location":"✈️","profile_link_color":"FFCC4D","profile_image_url":"http://pbs.twimg.com/profile_images/589150197432901632/M_T8-y56_normal.png","following":false,"geo_enabled":true,"profile_banner_url":"https://pbs.twimg.com/profile_banners/2361194822/1418240906","profile_background_image_url":"http://pbs.twimg.com/profile_background_images/480467914462461952/9CkWm3oY.jpeg","name":"Selena Gomez","lang":"es","profile_background_tile":true,"favourites_count":2030,"screen_name":"selenaftprada","notifications":false,"url":"http://t.co/xCtMQBjXGd","created_at":"Tue Feb 25 14:45:16 +0000 2014","contributors_enabled":false,"time_zone":"Athens","protected":false,"default_profile":false,"is_translator":false},"geo":null,"in_reply_to_user_id_str":"2792309533","lang":"und","created_at":"Mon Dec 15 19:10:28 +0000 2014","in_reply_to_status_id_str":"544570006244048896","place":{"full_name":"Grand Prairie, TX","url":"https://api.twitter.com/1.1/geo/id/a9b50065bfbb3fa9.json","country":"United States","place_type":"city","bounding_box":{"type":"Polygon","coordinates":[[[-97.065649,32.720529],[-96.924017,32.720529],[-96.924017,32.816653],[-97.065649,32.816653]]]},"contained_within":[],"country_code":"US","attributes":{},"id":"a9b50065bfbb3fa9","name":"Grand Prairie"}},
{"contributors":null,"truncated":false,"text":"@saeedbadshah50 @KhaledBeydoun who cares","in_reply_to_status_id":544570171218612224,"id":544570264143790080,"favorite_count":0,"source":"<a href=\"http://twitter.com\" rel=\"nofollow\">Twitter Web Client</a>","retweeted":false,"coordinates":null,"entities":{"symbols":[],"user_mentions":[{"id":2792309533,"indices":[0,15],"id_str":"2792309533","screen_name":"saeedbadshah50","name":"saeed badshah"},{"id":2163076560,"indices":[16,30],"id_str":"2163076560","screen_name":"KhaledBeydoun","name":"Khaled Bey"}],"hashtags":[],"urls":[]},"in_reply_to_screen_name":"saeedbadshah50","id_str":"544570264143790080","retweet_count":0,"in_reply_to_user_id":2792309533,"favorited":false,"user":{"follow_request_sent":false,"profile_use_background_image":true,"profile_text_color":"3C3940","default_profile_image":false,"id":2361194822,"profile_background_image_url_https":"https://pbs.twimg.com/profile_background_images/480467914462461952/9CkWm3oY.jpeg","verified":false,"profile_location":null,"profile_image_url_https":"https://pbs.twimg.com/profile_images/589150197432901632/M_T8-y56_normal.png","profile_sidebar_fill_color":"95E8EC","entities":{"url":{"urls":[{"url":"http://t.co/xCtMQBjXGd","indices":[0,22],"expanded_url":"http://ask.fm/selenagismyidol","display_url":"ask.fm/selenagismyidol"}]},"description":{"urls":[]}},"followers_count":5320,"profile_sidebar_border_color":"FFFFFF","id_str":"2361194822","profile_background_color":"0099B9","listed_count":17,"is_translation_enabled":false,"utc_offset":7200,"statuses_count":17008,"description":"Here for Selena, not for your opinion. Love yourself first.","friends_count":4296,"location":"✈️","profile_link_color":"FFCC4D","profile_image_url":"http://pbs.twimg.com/profile_images/589150197432901632/M_T8-y56_normal.png","following":false,"geo_enabled":true,"profile_banner_url":"https://pbs.twimg.com/profile_banners/2361194822/1418240906","profile_background_image_url":"http://pbs.twimg.com/profile_background_images/480467914462461952/9CkWm3oY.jpeg","name":"Selena Gomez","lang":"es","profile_background_tile":true,"favourites_count":2030,"screen_name":"selenaftprada","notifications":false,"url":"http://t.co/xCtMQBjXGd","created_at":"Tue Feb 25 14:45:16 +0000 2014","contributors_enabled":false,"time_zone":"Athens","protected":false,"default_profile":false,"is_translator":false},"geo":null,"in_reply_to_user_id_str":"2792309533","lang":"en","created_at":"Mon Dec 15 19:10:43 +0000 2014","in_reply_to_status_id_str":"544570171218612224","place":{"full_name":"Grand Prairie, TX","url":"https://api.twitter.com/1.1/geo/id/a9b50065bfbb3fa9.json","country":"United States","place_type":"city","bounding_box":{"type":"Polygon","coordinates":[[[-97.065649,32.720529],[-96.924017,32.720529],[-96.924017,32.816653],[-97.065649,32.816653]]]},"contained_within":[],"country_code":"US","attributes":{},"id":"a9b50065bfbb3fa9","name":"Grand Prairie"}},
{"contributors":null,"truncated":false,"text":"@selenaftprada @KhaledBeydoun tell me","in_reply_to_status_id":544570264143790080,"id":544570383777538048,"favorite_count":0,"source":"<a href=\"http://twitter.com/download/android\" rel=\"nofollow\">Twitter for Android</a>","retweeted":false,"coordinates":null,"entities":{"symbols":[],"user_mentions":[{"id":2361194822,"indices":[0,14],"id_str":"2361194822","screen_name":"selenaftprada","name":"Selena Gomez"},{"id":2163076560,"indices":[15,29],"id_str":"2163076560","screen_name":"KhaledBeydoun","name":"Khaled Bey"}],"hashtags":[],"urls":[]},"in_reply_to_screen_name":"selenaftprada","id_str":"544570383777538048","retweet_count":0,"in_reply_to_user_id":2361194822,"favorited":false,"user":{"follow_request_sent":false,"profile_use_background_image":true,"profile_text_color":"333333","default_profile_image":false,"id":2792309533,"profile_background_image_url_https":"https://abs.twimg.com/images/themes/theme1/bg.png","verified":false,"profile_location":null,"profile_image_url_https":"https://pbs.twimg.com/profile_images/507965571577569280/GjSmBb5p_normal.jpeg","profile_sidebar_fill_color":"DDEEF6","entities":{"description":{"urls":[]}},"followers_count":15,"profile_sidebar_border_color":"C0DEED","id_str":"2792309533","profile_background_color":"C0DEED","listed_count":0,"is_translation_enabled":false,"utc_offset":null,"statuses_count":56,"description":"","friends_count":212,"location":"","profile_link_color":"0084B4","profile_image_url":"http://pbs.twimg.com/profile_images/507965571577569280/GjSmBb5p_normal.jpeg","following":false,"geo_enabled":false,"profile_background_image_url":"http://abs.twimg.com/images/themes/theme1/bg.png","name":"saeed badshah","lang":"en","profile_background_tile":false,"favourites_count":15,"screen_name":"saeedbadshah50","notifications":false,"url":null,"created_at":"Fri Sep 05 16:33:11 +0000 2014","contributors_enabled":false,"time_zone":null,"protected":false,"default_profile":true,"is_translator":false},"geo":null,"in_reply_to_user_id_str":"2361194822","lang":"en","created_at":"Mon Dec 15 19:11:11 +0000 2014","in_reply_to_status_id_str":"544570264143790080","place":null},
{"contributors":null,"truncated":false,"text":"@selenaftprada @KhaledBeydoun I dont know u","in_reply_to_status_id":544570264143790080,"id":544570429646462976,"favorite_count":0,"source":"<a href=\"http://twitter.com/download/android\" rel=\"nofollow\">Twitter for Android</a>","retweeted":false,"coordinates":null,"entities":{"symbols":[],"user_mentions":[{"id":2361194822,"indices":[0,14],"id_str":"2361194822","screen_name":"selenaftprada","name":"Selena Gomez"},{"id":2163076560,"indices":[15,29],"id_str":"2163076560","screen_name":"KhaledBeydoun","name":"Khaled Bey"}],"hashtags":[],"urls":[]},"in_reply_to_screen_name":"selenaftprada","id_str":"544570429646462976","retweet_count":0,"in_reply_to_user_id":2361194822,"favorited":false,"user":{"follow_request_sent":false,"profile_use_background_image":true,"profile_text_color":"333333","default_profile_image":false,"id":2792309533,"profile_background_image_url_https":"https://abs.twimg.com/images/themes/theme1/bg.png","verified":false,"profile_location":null,"profile_image_url_https":"https://pbs.twimg.com/profile_images/507965571577569280/GjSmBb5p_normal.jpeg","profile_sidebar_fill_color":"DDEEF6","entities":{"description":{"urls":[]}},"followers_count":15,"profile_sidebar_border_color":"C0DEED","id_str":"2792309533","profile_background_color":"C0DEED","listed_count":0,"is_translation_enabled":false,"utc_offset":null,"statuses_count":56,"description":"","friends_count":212,"location":"","profile_link_color":"0084B4","profile_image_url":"http://pbs.twimg.com/profile_images/507965571577569280/GjSmBb5p_normal.jpeg","following":false,"geo_enabled":false,"profile_background_image_url":"http://abs.twimg.com/images/themes/theme1/bg.png","name":"saeed badshah","lang":"en","profile_background_tile":false,"favourites_count":15,"screen_name":"saeedbadshah50","notifications":false,"url":null,"created_at":"Fri Sep 05 16:33:11 +0000 2014","contributors_enabled":false,"time_zone":null,"protected":false,"default_profile":true,"is_translator":false},"geo":null,"in_reply_to_user_id_str":"2361194822","lang":"en","created_at":"Mon Dec 15 19:11:22 +0000 2014","in_reply_to_status_id_str":"544570264143790080","place":null},
{"contributors":null,"truncated":false,"text":"@saeedbadshah50 @KhaledBeydoun thats why i wont tell you","in_reply_to_status_id":544570429646462976,"id":544570601470713856,"favorite_count":0,"source":"<a href=\"http://twitter.com\" rel=\"nofollow\">Twitter Web Client</a>","retweeted":false,"coordinates":null,"entities":{"symbols":[],"user_mentions":[{"id":2792309533,"indices":[0,15],"id_str":"2792309533","screen_name":"saeedbadshah50","name":"saeed badshah"},{"id":2163076560,"indices":[16,30],"id_str":"2163076560","screen_name":"KhaledBeydoun","name":"Khaled Bey"}],"hashtags":[],"urls":[]},"in_reply_to_screen_name":"saeedbadshah50","id_str":"544570601470713856","retweet_count":0,"in_reply_to_user_id":2792309533,"favorited":false,"user":{"follow_request_sent":false,"profile_use_background_image":true,"profile_text_color":"3C3940","default_profile_image":false,"id":2361194822,"profile_background_image_url_https":"https://pbs.twimg.com/profile_background_images/480467914462461952/9CkWm3oY.jpeg","verified":false,"profile_location":null,"profile_image_url_https":"https://pbs.twimg.com/profile_images/589150197432901632/M_T8-y56_normal.png","profile_sidebar_fill_color":"95E8EC","entities":{"url":{"urls":[{"url":"http://t.co/xCtMQBjXGd","indices":[0,22],"expanded_url":"http://ask.fm/selenagismyidol","display_url":"ask.fm/selenagismyidol"}]},"description":{"urls":[]}},"followers_count":5320,"profile_sidebar_border_color":"FFFFFF","id_str":"2361194822","profile_background_color":"0099B9","listed_count":17,"is_translation_enabled":false,"utc_offset":7200,"statuses_count":17008,"description":"Here for Selena, not for your opinion. Love yourself first.","friends_count":4296,"location":"✈️","profile_link_color":"FFCC4D","profile_image_url":"http://pbs.twimg.com/profile_images/589150197432901632/M_T8-y56_normal.png","following":false,"geo_enabled":true,"profile_banner_url":"https://pbs.twimg.com/profile_banners/2361194822/1418240906","profile_background_image_url":"http://pbs.twimg.com/profile_background_images/480467914462461952/9CkWm3oY.jpeg","name":"Selena Gomez","lang":"es","profile_background_tile":true,"favourites_count":2030,"screen_name":"selenaftprada","notifications":false,"url":"http://t.co/xCtMQBjXGd","created_at":"Tue Feb 25 14:45:16 +0000 2014","contributors_enabled":false,"time_zone":"Athens","protected":false,"default_profile":false,"is_translator":false},"geo":null,"in_reply_to_user_id_str":"2792309533","lang":"en","created_at":"Mon Dec 15 19:12:03 +0000 2014","in_reply_to_status_id_str":"544570429646462976","place":{"full_name":"Grand Prairie, TX","url":"https://api.twitter.com/1.1/geo/id/a9b50065bfbb3fa9.json","country":"United States","place_type":"city","bounding_box":{"type":"Polygon","coordinates":[[[-97.065649,32.720529],[-96.924017,32.720529],[-96.924017,32.816653],[-97.065649,32.816653]]]},"contained_within":[],"country_code":"US","attributes":{},"id":"a9b50065bfbb3fa9","name":"Grand Prairie"}},
{"contributors":null,"truncated":false,"text":"@saeedbadshah50 @KhaledBeydoun goodbye.","in_reply_to_status_id":544570429646462976,"id":544570693091065856,"favorite_count":0,"source":"<a href=\"http://twitter.com\" rel=\"nofollow\">Twitter Web Client</a>","retweeted":false,"coordinates":null,"entities":{"symbols":[],"user_mentions":[{"id":2792309533,"indices":[0,15],"id_str":"2792309533","screen_name":"saeedbadshah50","name":"saeed badshah"},{"id":2163076560,"indices":[16,30],"id_str":"2163076560","screen_name":"KhaledBeydoun","name":"Khaled Bey"}],"hashtags":[],"urls":[]},"in_reply_to_screen_name":"saeedbadshah50","id_str":"544570693091065856","retweet_count":0,"in_reply_to_user_id":2792309533,"favorited":false,"user":{"follow_request_sent":false,"profile_use_background_image":true,"profile_text_color":"3C3940","default_profile_image":false,"id":2361194822,"profile_background_image_url_https":"https://pbs.twimg.com/profile_background_images/480467914462461952/9CkWm3oY.jpeg","verified":false,"profile_location":null,"profile_image_url_https":"https://pbs.twimg.com/profile_images/589150197432901632/M_T8-y56_normal.png","profile_sidebar_fill_color":"95E8EC","entities":{"url":{"urls":[{"url":"http://t.co/xCtMQBjXGd","indices":[0,22],"expanded_url":"http://ask.fm/selenagismyidol","display_url":"ask.fm/selenagismyidol"}]},"description":{"urls":[]}},"followers_count":5320,"profile_sidebar_border_color":"FFFFFF","id_str":"2361194822","profile_background_color":"0099B9","listed_count":17,"is_translation_enabled":false,"utc_offset":7200,"statuses_count":17042,"description":"Here for Selena, not for your opinion. Love yourself first.","friends_count":4297,"location":"✈️","profile_link_color":"FFCC4D","profile_image_url":"http://pbs.twimg.com/profile_images/589150197432901632/M_T8-y56_normal.png","following":false,"geo_enabled":true,"profile_banner_url":"https://pbs.twimg.com/profile_banners/2361194822/1418240906","profile_background_image_url":"http://pbs.twimg.com/profile_background_images/480467914462461952/9CkWm3oY.jpeg","name":"Selena Gomez","lang":"es","profile_background_tile":true,"favourites_count":2034,"screen_name":"selenaftprada","notifications":false,"url":"http://t.co/xCtMQBjXGd","created_at":"Tue Feb 25 14:45:16 +0000 2014","contributors_enabled":false,"time_zone":"Athens","protected":false,"default_profile":false,"is_translator":false},"geo":null,"in_reply_to_user_id_str":"2792309533","lang":"en","created_at":"Mon Dec 15 19:12:25 +0000 2014","in_reply_to_status_id_str":"544570429646462976","place":{"full_name":"Grand Prairie, TX","url":"https://api.twitter.com/1.1/geo/id/a9b50065bfbb3fa9.json","country":"United States","place_type":"city","bounding_box":{"type":"Polygon","coordinates":[[[-97.065649,32.720529],[-96.924017,32.720529],[-96.924017,32.816653],[-97.065649,32.816653]]]},"contained_within":[],"country_code":"US","attributes":{},"id":"a9b50065bfbb3fa9","name":"Grand Prairie"}},
{"contributors":null,"truncated":false,"text":"@selenaftprada @KhaledBeydoun ok","in_reply_to_status_id":544570693091065856,"id":544570862112755712,"favorite_count":0,"source":"<a href=\"http://twitter.com/download/android\" rel=\"nofollow\">Twitter for Android</a>","retweeted":false,"coordinates":null,"entities":{"symbols":[],"user_mentions":[{"id":2361194822,"indices":[0,14],"id_str":"2361194822","screen_name":"selenaftprada","name":"Selena Gomez"},{"id":2163076560,"indices":[15,29],"id_str":"2163076560","screen_name":"KhaledBeydoun","name":"Khaled Bey"}],"hashtags":[],"urls":[]},"in_reply_to_screen_name":"selenaftprada","id_str":"544570862112755712","retweet_count":0,"in_reply_to_user_id":2361194822,"favorited":false,"user":{"follow_request_sent":false,"profile_use_background_image":true,"profile_text_color":"333333","default_profile_image":false,"id":2792309533,"profile_background_image_url_https":"https://abs.twimg.com/images/themes/theme1/bg.png","verified":false,"profile_location":null,"profile_image_url_https":"https://pbs.twimg.com/profile_images/507965571577569280/GjSmBb5p_normal.jpeg","profile_sidebar_fill_color":"DDEEF6","entities":{"description":{"urls":[]}},"followers_count":15,"profile_sidebar_border_color":"C0DEED","id_str":"2792309533","profile_background_color":"C0DEED","listed_count":0,"is_translation_enabled":false,"utc_offset":null,"statuses_count":56,"description":"","friends_count":212,"location":"","profile_link_color":"0084B4","profile_image_url":"http://pbs.twimg.com/profile_images/507965571577569280/GjSmBb5p_normal.jpeg","following":false,"geo_enabled":false,"profile_background_image_url":"http://abs.twimg.com/images/themes/theme1/bg.png","name":"saeed badshah","lang":"en","profile_background_tile":false,"favourites_count":15,"screen_name":"saeedbadshah50","notifications":false,"url":null,"created_at":"Fri Sep 05 16:33:11 +0000 2014","contributors_enabled":false,"time_zone":null,"protected":false,"default_profile":true,"is_translator":false},"geo":null,"in_reply_to_user_id_str":"2361194822","lang":"und","created_at":"Mon Dec 15 19:13:05 +0000 2014","in_reply_to_status_id_str":"544570693091065856","place":null}
]